autowordle/__init__.py
autowordle/__main__.py
autowordle/archiver.py
autowordle/collect.py
autowordle/collect_tk.py
autowordle/db.py
autowordle/desktop.py
autowordle/ipc.py
autowordle/mkimg.py
autowordle/prog.py
autowordle/timer.py
autowordle/game/__init__.py
autowordle/game/detect.py
autowordle/game/parse.py
autowordle/game/reparse.py
autowordle/res/__init__.py
autowordle/res/ddown.png
autowordle/res/down.png
autowordle/res/dup.png
autowordle/res/emblem-default-symbolic.png
autowordle/res/emblem-error.png
autowordle/res/emblem-question.png
autowordle/res/emblem-readonly.png
autowordle/res/emblem-remove.png
autowordle/res/game_defs.toml
autowordle/res/games.yaml
autowordle/res/left.png
autowordle/res/lr.png
autowordle/res/missing-image.png
autowordle/res/multi.png
autowordle/res/redactle-base.png
autowordle/res/redactle-base.sh
autowordle/res/right-new.png
autowordle/res/right.png
autowordle/res/schema.sql
autowordle/res/ud.png
autowordle/res/up-old.png
autowordle/res/up.png
autowordle-2.3.5.dist-info/licenses/LICENSE
autowordle-2.3.5.dist-info/METADATA
autowordle-2.3.5.dist-info/WHEEL
autowordle-2.3.5.dist-info/entry_points.txt
autowordle-2.3.5.dist-info/top_level.txt
autowordle-2.3.5.dist-info/RECORD
