Metadata-Version: 2.4
Name: autowordle
Version: 2.3.5
Summary: Automatic Wordle collector
Requires-Python: >=3.12
License-File: LICENSE
Requires-Dist: maturin>=1.8.2
Requires-Dist: pillow>=11.1.0
Requires-Dist: platformdirs>=3.10.0
Requires-Dist: pytesseract>=0.3.13
Requires-Dist: pytz>=2025.1
Requires-Dist: pyxdg>=0.28
Requires-Dist: pyyaml>=6.0.2
Requires-Dist: toml>=0.10.2
Requires-Dist: ttkthemes>=3.2.2
Requires-Dist: wand>=0.6.13
Provides-Extra: activitywatch
Requires-Dist: aw-client>=0.5.15; extra == "activitywatch"
Dynamic: license-file
